places_summarized/__init__.py
places_summarized/client.py
places_summarized/errors.py
places_summarized/fake_client.py
places_summarized/summary.py
places_summarized/test.py
places_summarized/data/sydney.json
places_summarized-0.1.1.dist-info/LICENSE
places_summarized-0.1.1.dist-info/METADATA
places_summarized-0.1.1.dist-info/WHEEL
places_summarized-0.1.1.dist-info/top_level.txt
places_summarized-0.1.1.dist-info/RECORD
