Metadata-Version: 2.1
Name: places-summarized
Version: 0.1.1
Summary: Summarizing the Google Maps attributes of places within a specified area
Home-page: https://github.com/juandes/places-summarized
Author: Juan De Dios Santos
Author-email: author@example.com
License: UNKNOWN
Platform: UNKNOWN
Classifier: Programming Language :: Python :: 3
Classifier: License :: OSI Approved :: MIT License
Classifier: Intended Audience :: Developers
Requires-Python: >=3.6
Requires-Dist: googlemaps (>=3.1.4)
